{"sourceTree":{"name":"virtual_root","children":[{"name":"Servers","children":[{"name":"SQL Server - localhost:1433:ieaccountinginusd","children":[{"name":"Databases","children":[{"name":"IEAccountinginUSD"}]}]}]},{"name":"noSQL Clusters"},{"name":"ETL"}]},"targetTree":{"name":"virtual_root","children":[{"name":"Servers","children":[{"name":"PostgreSQL - localhost:54321:ieaccountinginusd","children":[{"name":"Schemas","children":[{"name":"aws_sqlserver_ext"}]},{"name":"Foreign Servers"},{"name":"Server Level Objects"},{"name":"SQL Scripts"}]}]},{"name":"noSQL Clusters"},{"name":"ETL"}]}}